keystroke_transcriber/__init__.py
keystroke_transcriber/__main__.py
keystroke_transcriber/constants.py
keystroke_transcriber/output_writer.py
keystroke_transcriber/recorder.py
keystroke_transcriber/utils.py
keystroke_transcriber/output_writers/__init__.py
keystroke_transcriber/output_writers/digispark.py
keystroke_transcriber-1.0.1.dist-info/LICENSE
keystroke_transcriber-1.0.1.dist-info/METADATA
keystroke_transcriber-1.0.1.dist-info/WHEEL
keystroke_transcriber-1.0.1.dist-info/top_level.txt
keystroke_transcriber-1.0.1.dist-info/RECORD
