Metadata-Version: 2.1
Name: keystroke-transcriber
Version: 1.0.1
Summary: Records keypress events and converts them for replay on programmable USB HID devices
Home-page: https://github.com/eriknyquist/keystroke_transcriber
Author: Erik Nyquist
Author-email: eknyquist@gmail.com
License: Apache 2.0
Platform: UNKNOWN
Requires-Dist: keyboard
Requires-Dist: wheel
